wayfarer/__init__.py
wayfarer/wayfarer.py
envelope_ai-0.0.7.dist-info/METADATA
envelope_ai-0.0.7.dist-info/WHEEL
envelope_ai-0.0.7.dist-info/licenses/LICENSE
envelope_ai-0.0.7.dist-info/RECORD
