Metadata-Version: 2.1
Name: envelope-ai
Version: 0.0.7
Summary: SDK for envelope DB
Project-URL: Homepage, https://github.com/envelope-ai/wayfarer
Project-URL: Bug Tracker, https://github.com/envelope-ai/wayfarer/issues
Author-email: "envelope.ai" <support@envelope.ai>
License-File: LICENSE
Classifier: License :: OSI Approved :: MIT License
Classifier: Operating System :: OS Independent
Classifier: Programming Language :: Python :: 3
Requires-Python: >=3.7
Requires-Dist: requests~=2.28
Requires-Dist: validators~=0.20
